waldur_site_agent_slurm/__init__.py
waldur_site_agent_slurm/backend.py
waldur_site_agent_slurm/client.py
waldur_site_agent_slurm/historical_usage_loader.py
waldur_site_agent_slurm/parser.py
waldur_site_agent_slurm/schemas.py
waldur_site_agent_slurm/utils.py
waldur_site_agent_slurm-0.8.2.dist-info/METADATA
waldur_site_agent_slurm-0.8.2.dist-info/WHEEL
waldur_site_agent_slurm-0.8.2.dist-info/entry_points.txt
waldur_site_agent_slurm-0.8.2.dist-info/RECORD
